gaunit/GAUnit.py
gaunit/__about__.py
gaunit/__init__.py
gaunit/config.json
gaunit-0.0.5.dist-info/LICENSE
gaunit-0.0.5.dist-info/METADATA
gaunit-0.0.5.dist-info/WHEEL
gaunit-0.0.5.dist-info/top_level.txt
gaunit-0.0.5.dist-info/RECORD
