Metadata-Version: 2.1
Name: gaunit
Version: 0.0.5
Summary: Testing Google Analytics implementations within CI pipelines
Home-page: https://github.com/VinceCabs/GAUnit
Author: Vincent Cabanis
Author-email: touch@cabanis.fr
License: MIT
Platform: UNKNOWN
Classifier: Development Status :: 3 - Alpha
Classifier: Programming Language :: Python :: 3
Classifier: License :: OSI Approved :: MIT License
Classifier: Operating System :: OS Independent
Classifier: Topic :: Software Development :: Testing
Requires-Python: >=3.6
Requires-Dist: selenium
Requires-Dist: browsermob-proxy
